my_uv_demo/__init__.py
my_uv_demo/core.py
my_uv_demo-0.1.1.dist-info/METADATA
my_uv_demo-0.1.1.dist-info/WHEEL
my_uv_demo-0.1.1.dist-info/entry_points.txt
my_uv_demo-0.1.1.dist-info/RECORD
