Metadata-Version: 2.4
Name: my-uv-demo
Version: 0.1.1
Summary: A demo project for UV publishing
Author-email: 刘明轩 <13840348310@163.com>
Requires-Python: >=3.11
Requires-Dist: requests>=2.25
